odoo/addons/product_view_inventory_no_search_default_my_count/README.rst
odoo/addons/product_view_inventory_no_search_default_my_count/__init__.py
odoo/addons/product_view_inventory_no_search_default_my_count/__manifest__.py
odoo/addons/product_view_inventory_no_search_default_my_count/i18n/it.po
odoo/addons/product_view_inventory_no_search_default_my_count/i18n/product_view_inventory_no_search_default_my_count.pot
odoo/addons/product_view_inventory_no_search_default_my_count/models/__init__.py
odoo/addons/product_view_inventory_no_search_default_my_count/models/stock_quant.py
odoo/addons/product_view_inventory_no_search_default_my_count/readme/CONTEXT.rst
odoo/addons/product_view_inventory_no_search_default_my_count/readme/DESCRIPTION.rst
odoo/addons/product_view_inventory_no_search_default_my_count/static/description/icon.png
odoo/addons/product_view_inventory_no_search_default_my_count/static/description/index.html
odoo_addon_product_view_inventory_no_search_default_my_count-16.0.1.0.0.4.dist-info/METADATA
odoo_addon_product_view_inventory_no_search_default_my_count-16.0.1.0.0.4.dist-info/WHEEL
odoo_addon_product_view_inventory_no_search_default_my_count-16.0.1.0.0.4.dist-info/top_level.txt
odoo_addon_product_view_inventory_no_search_default_my_count-16.0.1.0.0.4.dist-info/RECORD
